biosip_tools/__init__.py
biosip_tools/eeg/__init__.py
biosip_tools/eeg/constants.py
biosip_tools/eeg/timeseries.py
biosip_tools/eeg/utils.py
Biosip_Tools-0.0.7.dist-info/LICENSE
Biosip_Tools-0.0.7.dist-info/METADATA
Biosip_Tools-0.0.7.dist-info/WHEEL
Biosip_Tools-0.0.7.dist-info/top_level.txt
Biosip_Tools-0.0.7.dist-info/RECORD
