Metadata-Version: 2.1
Name: Biosip-Tools
Version: 0.0.7
Summary: Tools for Biosip Group
Home-page: https://github.com/Skalextric/biosip_tools
Author: Biosip
License: UNKNOWN
Platform: UNKNOWN
Classifier: Programming Language :: Python :: 3
Classifier: License :: OSI Approved :: MIT License
Classifier: Operating System :: OS Independent
Requires-Python: >=3.6
License-File: LICENSE
Requires-Dist: numpy
Requires-Dist: mne
Requires-Dist: scipy
Requires-Dist: matplotlib
